MANIFEST.in
README.rst
env.sh
setup.py
bin/dimerize
bin/plread
bin/tune_replicas
dimerizer/__init__.py
dimerizer/alparser.py
dimerizer/opt.py
dimerizer.egg-info/PKG-INFO
dimerizer.egg-info/SOURCES.txt
dimerizer.egg-info/dependency_links.txt
dimerizer.egg-info/not-zip-safe
dimerizer.egg-info/top_level.txt
doc/alparser.m.html
doc/index.html
doc/opt.m.html
examples/examples
tables/build_em.py
tables/table.xvg
tables/table_INT1_INT1.xvg
tables/table_INT1_NONDIM.xvg
tables/table_INT2_INT2.xvg
tables/table_INT2_NONDIM.xvg
tables/table_INTF_INTF.xvg
tables/table_INTF_NONDIM.xvg
tables/table_NONDIM_INT1.xvg
tables/table_NONDIM_INT2.xvg
tables/table_NONDIM_INTF.xvg
tables/table_NONDIM_NONDIM.xvg
tables/tablep.xvg
unmodified_forcefield/desc