Metadata-Version: 1.1
Name: dimerizer
Version: 1.0.1
Summary: The dimerizer script for Dimer simulations in Gromacs
Home-page: http://github.com/marckn/dimerizer
Author: Marco Nava
Author-email: mark.nava@gmail.com
License: GPL
Keywords: protein simulation dimer gromacs forcefield
Platform: UNKNOWN
Classifier: Development Status :: 4 - Beta
Classifier: Intended Audience :: Science/Research
Classifier: License :: OSI Approved :: GNU General Public License (GPL)
Classifier: Natural Language :: English
Classifier: Programming Language :: Python :: 2.7
Classifier: Topic :: Scientific/Engineering :: Bio-Informatics
